itoutils/__init__.py
itoutils/pytest.py
itoutils/urls.py
itoutils/django/__init__.py
itoutils/django/apps.py
itoutils/django/commands.py
itoutils/django/logging.py
itoutils/django/testing.py
itoutils/django/nexus/__init__.py
itoutils/django/nexus/middleware.py
itoutils/django/nexus/token.py
itoutils/django/nexus/urls.py
itoutils/django/nexus/views.py
itoutils-25.12.22.1.dist-info/licenses/LICENSE
itoutils-25.12.22.1.dist-info/METADATA
itoutils-25.12.22.1.dist-info/WHEEL
itoutils-25.12.22.1.dist-info/entry_points.txt
itoutils-25.12.22.1.dist-info/top_level.txt
itoutils-25.12.22.1.dist-info/RECORD
