Metadata-Version: 2.4
Name: itoutils
Version: 25.12.22.1
Summary: GIP Plateforme de l'inclusion's utilities library
Project-URL: github, https://github.com/gip-inclusion/itoutils
Classifier: Development Status :: 5 - Production/Stable
Classifier: Intended Audience :: Developers
Classifier: Topic :: Software Development :: Libraries
Classifier: Programming Language :: Python :: 3
Classifier: Programming Language :: Python :: 3.12
Classifier: Programming Language :: Python :: 3.13
Classifier: Framework :: Django
Classifier: Framework :: Pytest
Requires-Python: >=3.12
License-File: LICENSE
Provides-Extra: django
Requires-Dist: django>=5.2; extra == "django"
Requires-Dist: django-datadog-logger>=0.7.3; extra == "django"
Requires-Dist: jwcrypto>=1.5.6; extra == "django"
Requires-Dist: psycopg[binary]>=3.2.12; extra == "django"
Provides-Extra: django-testing
Requires-Dist: django>=5.2; extra == "django-testing"
Requires-Dist: sqlparse; extra == "django-testing"
Requires-Dist: syrupy; extra == "django-testing"
Dynamic: license-file
